MANIFEST.in
README.md
README.zh-CN.md
requirements.txt
setup.py
keras_on_lstm.egg-info/PKG-INFO
keras_on_lstm.egg-info/SOURCES.txt
keras_on_lstm.egg-info/dependency_links.txt
keras_on_lstm.egg-info/requires.txt
keras_on_lstm.egg-info/top_level.txt
keras_ordered_neurons/__init__.py
keras_ordered_neurons/activations.py
keras_ordered_neurons/backend.py
keras_ordered_neurons/cntk_backend.py
keras_ordered_neurons/layers.py
tests/__init__.py
tests/test_activations.py
tests/test_cntk_backend.py
tests/test_layers.py