Metadata-Version: 2.1
Name: keras-on-lstm
Version: 0.8.0
Summary: Unofficial implementation of ON-LSTM
Home-page: https://github.com/CyberZHG/keras-ordered-neurons
Author: CyberZHG
Author-email: CyberZHG@gmail.com
License: Anti 996
Platform: UNKNOWN
Classifier: Programming Language :: Python :: 2.7
Classifier: Programming Language :: Python :: 3.6
Classifier: Operating System :: OS Independent
